bluemath_tk/__init__.py
bluemath_tk/_version.py
bluemath_tk/additive/__init__.py
bluemath_tk/additive/greensurge.py
bluemath_tk/config/__init__.py
bluemath_tk/config/paths.py
bluemath_tk/core/__init__.py
bluemath_tk/core/constants.py
bluemath_tk/core/dask.py
bluemath_tk/core/decorators.py
bluemath_tk/core/geo.py
bluemath_tk/core/io.py
bluemath_tk/core/logging.py
bluemath_tk/core/metrics.py
bluemath_tk/core/models.py
bluemath_tk/core/operations.py
bluemath_tk/core/data/__init__.py
bluemath_tk/core/data/sample_data.py
bluemath_tk/core/plotting/__init__.py
bluemath_tk/core/plotting/base_plotting.py
bluemath_tk/core/plotting/colors.py
bluemath_tk/core/plotting/satellite.py
bluemath_tk/core/plotting/scatter.py
bluemath_tk/core/plotting/utils.py
bluemath_tk/datamining/__init__.py
bluemath_tk/datamining/_base_datamining.py
bluemath_tk/datamining/kma.py
bluemath_tk/datamining/lhs.py
bluemath_tk/datamining/mda.py
bluemath_tk/datamining/pca.py
bluemath_tk/datamining/som.py
bluemath_tk/deeplearning/__init__.py
bluemath_tk/deeplearning/_base_model.py
bluemath_tk/deeplearning/autoencoders.py
bluemath_tk/deeplearning/gp_models.py
bluemath_tk/deeplearning/layers.py
bluemath_tk/deeplearning/regularizers.py
bluemath_tk/deeplearning/unet.py
bluemath_tk/distributions/__init__.py
bluemath_tk/distributions/_base_distributions.py
bluemath_tk/distributions/copula.py
bluemath_tk/distributions/extreme_correction.py
bluemath_tk/distributions/gev.py
bluemath_tk/distributions/gpd.py
bluemath_tk/distributions/nonstat_gev.py
bluemath_tk/distributions/pareto_poisson.py
bluemath_tk/distributions/poisson.py
bluemath_tk/distributions/pot.py
bluemath_tk/distributions/utils/extr_corr_utils.py
bluemath_tk/distributions/utils/pot_utils.py
bluemath_tk/downloaders/__init__.py
bluemath_tk/downloaders/_base_downloaders.py
bluemath_tk/downloaders/_download_result.py
bluemath_tk/downloaders/aviso/__init__.py
bluemath_tk/downloaders/aviso/aviso_downloader.py
bluemath_tk/downloaders/aviso/SWOT/SWOT_config.json
bluemath_tk-1.1.17.dist-info/licenses/LICENSE
bluemath_tk-1.1.17.dist-info/METADATA
bluemath_tk-1.1.17.dist-info/WHEEL
bluemath_tk-1.1.17.dist-info/top_level.txt
bluemath_tk-1.1.17.dist-info/RECORD
