Metadata-Version: 2.4
Name: bluemath-tk
Version: 1.1.17
Summary: Module collection for custom climate data analysis. The main objective of this Python package is to provide a set of statistical tools tailored for climate data analysis, with a focus on statistical classification and prediction.
Author-email: Geomatics and Ocean Engineering Group <bluemath@unican.es>
License:                     GNU GENERAL PUBLIC LICENSE
Project-URL: Homepage, https://github.com/GeoOcean/BlueMath_tk
Project-URL: Documentation, https://geoocean.github.io/BlueMath_tk/
Project-URL: Issues, https://github.com/GeoOcean/BlueMath_tk/issues
Keywords: climate,statistical,tools
Classifier: Programming Language :: Python :: 3 :: Only
Classifier: License :: OSI Approved :: GNU General Public License v3 (GPLv3)
Classifier: Operating System :: OS Independent
Classifier: Programming Language :: Python :: 3.11
Classifier: Programming Language :: Python :: 3.12
Requires-Python: >=3.11
License-File: LICENSE
Requires-Dist: requests
Requires-Dist: numpy
Requires-Dist: pandas
Requires-Dist: xarray
Requires-Dist: netcdf4
Requires-Dist: dask
Requires-Dist: distributed
Requires-Dist: zarr
Requires-Dist: scipy
Requires-Dist: scikit-learn
Requires-Dist: matplotlib
Requires-Dist: cartopy
Requires-Dist: jinja2
Requires-Dist: aiohttp
Requires-Dist: minisom
Requires-Dist: statsmodels
Requires-Dist: regionmask
Requires-Dist: ipykernel
Requires-Dist: ipywidgets
Requires-Dist: cmocean
Requires-Dist: siphon
Requires-Dist: plotly
Requires-Dist: h5py
Requires-Dist: prettytable
Requires-Dist: numba
Requires-Dist: csaps
Provides-Extra: docs
Requires-Dist: sphinx; extra == "docs"
Requires-Dist: sphinx-rtd-theme; extra == "docs"
Requires-Dist: jupyter-sphinx; extra == "docs"
Requires-Dist: myst-parser; extra == "docs"
Provides-Extra: tests
Requires-Dist: pytest; extra == "tests"
Requires-Dist: ruff; extra == "tests"
Provides-Extra: downloaders
Requires-Dist: cdsapi; extra == "downloaders"
Requires-Dist: ecmwf-opendata; extra == "downloaders"
Provides-Extra: waves
Requires-Dist: wavespectra; extra == "waves"
Requires-Dist: olas; extra == "waves"
Provides-Extra: numerical-models
Requires-Dist: hydromt-sfincs; extra == "numerical-models"
Provides-Extra: deeplearning
Requires-Dist: torch; extra == "deeplearning"
Requires-Dist: gpytorch; extra == "deeplearning"
Requires-Dist: optuna; extra == "deeplearning"
Provides-Extra: all
Requires-Dist: cdsapi; extra == "all"
Requires-Dist: ecmwf-opendata; extra == "all"
Requires-Dist: wavespectra; extra == "all"
Requires-Dist: olas; extra == "all"
Requires-Dist: hydromt-sfincs; extra == "all"
Requires-Dist: torch; extra == "all"
Requires-Dist: gpytorch; extra == "all"
Requires-Dist: optuna; extra == "all"
Dynamic: license-file
